README.md
setup.py
qoob/__id__.py
qoob/__init__.py
qoob/main.py
qoob.egg-info/PKG-INFO
qoob.egg-info/SOURCES.txt
qoob.egg-info/dependency_links.txt
qoob.egg-info/entry_points.txt
qoob.egg-info/requires.txt
qoob.egg-info/top_level.txt
qoob/backend/__init__.py
qoob/backend/cli.py
qoob/backend/library.py
qoob/backend/parser.py
qoob/backend/player.py
qoob/backend/tools.py
qoob/frontend/__init__.py
qoob/frontend/playlist.py
qoob/frontend/preferences.py
qoob/frontend/trinkets.py
qoob/icons/credits
qoob/icons/qoob.svg
qoob/icons/dark/art_off.svg
qoob/icons/dark/art_on.svg
qoob/icons/dark/collapse.svg
qoob/icons/dark/copy.svg
qoob/icons/dark/cut.svg
qoob/icons/dark/delete.svg
qoob/icons/dark/expand.svg
qoob/icons/dark/file.svg
qoob/icons/dark/filter_clear.svg
qoob/icons/dark/filter_hover.svg
qoob/icons/dark/folder.svg
qoob/icons/dark/next.svg
qoob/icons/dark/paste.svg
qoob/icons/dark/pause.svg
qoob/icons/dark/play.svg
qoob/icons/dark/preferences.svg
qoob/icons/dark/previous.svg
qoob/icons/dark/qoob.svg
qoob/icons/dark/quit.svg
qoob/icons/dark/refresh.svg
qoob/icons/dark/remove.svg
qoob/icons/dark/repeat_all.svg
qoob/icons/dark/repeat_off.svg
qoob/icons/dark/repeat_single.svg
qoob/icons/dark/reset.svg
qoob/icons/dark/shuffle_off.svg
qoob/icons/dark/shuffle_on.svg
qoob/icons/dark/stop.svg
qoob/icons/dark/tab_add.svg
qoob/icons/dark/tab_close.svg
qoob/icons/dark/tab_hover.svg
qoob/icons/light/art_off.svg
qoob/icons/light/art_on.svg
qoob/icons/light/collapse.svg
qoob/icons/light/copy.svg
qoob/icons/light/cut.svg
qoob/icons/light/delete.svg
qoob/icons/light/expand.svg
qoob/icons/light/file.svg
qoob/icons/light/filter_clear.svg
qoob/icons/light/filter_hover.svg
qoob/icons/light/folder.svg
qoob/icons/light/next.svg
qoob/icons/light/paste.svg
qoob/icons/light/pause.svg
qoob/icons/light/play.svg
qoob/icons/light/preferences.svg
qoob/icons/light/previous.svg
qoob/icons/light/qoob.svg
qoob/icons/light/quit.svg
qoob/icons/light/refresh.svg
qoob/icons/light/remove.svg
qoob/icons/light/repeat_all.svg
qoob/icons/light/repeat_off.svg
qoob/icons/light/repeat_single.svg
qoob/icons/light/reset.svg
qoob/icons/light/shuffle_off.svg
