Metadata-Version: 1.1
Name: qoob
Version: 0.2.1
Summary: foobar-like music player for Linux
Home-page: https://gitlab.com/william.belanger/qoob
Author: William Belanger
Author-email: UNKNOWN
License: UNKNOWN
Keywords: music folder player audio media linux
Platform: UNKNOWN
Classifier: Development Status :: 4 - Beta
Classifier: License :: OSI Approved :: GNU General Public License v3 (GPLv3)
Classifier: Programming Language :: Python :: 3.6
Classifier: Programming Language :: Python :: 3.7
